odoo/addons/invoice_report_hide_price/README.rst
odoo/addons/invoice_report_hide_price/__init__.py
odoo/addons/invoice_report_hide_price/__manifest__.py
odoo/addons/invoice_report_hide_price/models/__init__.py
odoo/addons/invoice_report_hide_price/models/account_move.py
odoo/addons/invoice_report_hide_price/models/account_move_line.py
odoo/addons/invoice_report_hide_price/readme/CONTRIBUTORS.rst
odoo/addons/invoice_report_hide_price/readme/DESCRIPTION.rst
odoo/addons/invoice_report_hide_price/readme/USAGE.rst
odoo/addons/invoice_report_hide_price/report/report_invoice.xml
odoo/addons/invoice_report_hide_price/static/description/icon.png
odoo/addons/invoice_report_hide_price/static/description/index.html
odoo/addons/invoice_report_hide_price/views/account_move_views.xml
odoo_addon_invoice_report_hide_price-15.0.1.0.0.2.dist-info/METADATA
odoo_addon_invoice_report_hide_price-15.0.1.0.0.2.dist-info/WHEEL
odoo_addon_invoice_report_hide_price-15.0.1.0.0.2.dist-info/top_level.txt
odoo_addon_invoice_report_hide_price-15.0.1.0.0.2.dist-info/RECORD
